src/BCD.v
module BCD (
    input [3:0] inp,  
    input clk2,
    output reg [3:0] bcd
  );

  reg  algo = 0;

  always@(posedge clk2) begin
    case(algo)
      0:begin
        bcd<=inp%10;
        algo <= 1;
        end
      1:begin
        bcd<=(inp-inp%10)/10;
        algo <= 0;
        end
    endcase
  end
endmodule

src/BCD_tb.v
`timescale 1ns/1ps //(unidad de tiempo)/(resolución)
`include "src/BCD.v"

module BCD_tb();
    reg [3:0] inp; 
    wire [3:0] bcdw_tb;
    reg  clk2;
    
    BCD uut (
        .inp(inp), 
        .bcd(bcdw_tb),
        .clk2(clk2)        
    );
   

    initial begin 
        inp = 4'b1111;
        clk2 = 0;  
    end
    always #5 clk2 =~clk2;
    
    initial begin
      $dumpfile("BCD_tb.vcd");
      $dumpvars(-1,uut);
      #80 $finish;
    end

endmodule

build/BCD_tb.vcd
$date
	Thu Jun 19 13:18:08 2025
$end
$version
	Icarus Verilog
$end
$timescale
	1ps
$end
$scope module BCD_tb $end
$scope module uut $end
$var wire 1 ! clk2 $end
$var wire 4 " inp [3:0] $end
$var reg 1 # algo $end
$var reg 4 $ bcd [3:0] $end
$upscope $end
$upscope $end
$enddefinitions $end
$comment Show the parameter values. $end
$dumpall
$end
#0
$dumpvars
bx $
0#
b1111 "
0!
$end
#5000
1#
b101 $
1!
#10000
0!
#15000
0#
b1 $
1!
#20000
0!
#25000
1#
b101 $
1!
#30000
0!
#35000
0#
b1 $
1!
#40000
0!
#45000
1#
b101 $
1!
#50000
0!
#55000
0#
b1 $
1!
#60000
0!
#65000
1#
b101 $
1!
#70000
0!
#75000
0#
b1 $
1!
