src/BCDtoSSeg.v
module BCDtoSSeg (
    input [3:0] BCD, 
    input [3:0] c,
    output reg [0:6] SSeg, 
    output [3:0] an
  );
  
  assign an = c;

  always @ ( * ) begin
    case (BCD)
      4'b0000: SSeg = 7'b0000001; // "0"  
  	  4'b0001: SSeg = 7'b1001111; // "1" 
  	  4'b0010: SSeg = 7'b0010010; // "2" 
  	  4'b0011: SSeg = 7'b0000110; // "3" 
  	  4'b0100: SSeg = 7'b1001100; // "4" 
  	  4'b0101: SSeg = 7'b0100100; // "5" 
  	  4'b0110: SSeg = 7'b0100000; // "6" 
  	  4'b0111: SSeg = 7'b0001111; // "7" 
  	  4'b1000: SSeg = 7'b0000000; // "8"  
  	  4'b1001: SSeg = 7'b0000100; // "9"
      4'b1100: SSeg = 7'b1111110; // menos
      4'ha: SSeg = 7'b0001000;  
      4'hb: SSeg = 7'b1100000;
      4'hc: SSeg = 7'b0110001;
      4'hd: SSeg = 7'b1000010;
      4'he: SSeg = 7'b0110000;
      4'hf: SSeg = 7'b0111000;
       default: SSeg = 7'b0000000;
    endcase
  end

endmodule

src/BCD.v
module BCD (
    input [3:0] inp,  
    input clk2,
    input rst,
    output reg [3:0] bcd,
    output reg [3:0] c
  );

  //reg  algo = 0; esto se cambia por el rst
  reg algo;

  always @* begin
      if (algo == 0)
        c = 4'b0001;
      else 
        c = 4'b0010;
  end
  always@(posedge clk2 or posedge rst) begin
    if (rst) begin
      algo <= 0;
      bcd <= 0;
    end else begin
      case(algo)
        0:begin
          bcd<=inp%10;
          algo <= 1;
          end
        1:begin
          bcd<=(inp-inp%10)/10;
          algo <= 0;
          end
      endcase
    end
  end
endmodule

src/top.v

`include "src/BCD.v"
`include "src/BCDtoSSeg.v"

module top (
    input [3:0] inp,  
    input clk2,
    input rst,
    output [0:6] SSeg, 
    output [3:0] an

);
    wire [3:0]bcdsseg;
    wire [3:0]c;

    BCD BCD(
    .bcd(bcdsseg),
    .inp(inp),
    .rst(rst),
    .c(c),
    .clk2(clk2)
    );

    BCDtoSSeg BCDtoSSeg(
    .SSeg(SSeg),
    .c(c),
    .BCD(bcdsseg),
    .an(an)
    );

endmodule

src/tb_top.v
`timescale 1ns/1ps //(unidad de tiempo)/(resolución)
`include "src/top.v"

module tb_top ();
    reg [3:0] inp;
    reg clk2;
    reg rst;
    wire [0:6] SSeg;
    wire [3:0] an;

    top uut(
    .inp(inp),
    .clk2(clk2),
    .rst(rst),
    .SSeg(SSeg),
    .an(an)
    );

    initial begin 
        inp = 4'b1111;
        clk2 = 0;
        rst = 1;
        #3 rst = 0;  // libera el reset  
    end
    always #5 clk2 = ~clk2;
    
    initial begin
      $dumpfile("tb_top.vcd");
      $dumpvars(-1,uut);
      #80 $finish;
    end

endmodule

build/tb_top.vcd
$date
	Tue Jun 24 23:06:35 2025
$end
$version
	Icarus Verilog
$end
$timescale
	1ps
$end
$scope module tb_top $end
$scope module uut $end
$var wire 1 ! clk2 $end
$var wire 4 " inp [3:0] $end
$var wire 1 # rst $end
$var wire 4 $ c [3:0] $end
$var wire 4 % bcdsseg [3:0] $end
$var wire 4 & an [3:0] $end
$var wire 7 ' SSeg [0:6] $end
$scope module BCD $end
$var wire 1 ! clk2 $end
$var wire 4 ( inp [3:0] $end
$var wire 1 # rst $end
$var reg 1 ) algo $end
$var reg 4 * bcd [3:0] $end
$var reg 4 + c [3:0] $end
$upscope $end
$scope module BCDtoSSeg $end
$var wire 4 , BCD [3:0] $end
$var wire 4 - an [3:0] $end
$var wire 4 . c [3:0] $end
$var reg 7 / SSeg [0:6] $end
$upscope $end
$upscope $end
$upscope $end
$enddefinitions $end
$comment Show the parameter values. $end
$dumpall
$end
#0
$dumpvars
b1 /
b1 .
b1 -
b0 ,
b1 +
b0 *
0)
b1111 (
b1 '
b1 &
b0 %
b1 $
1#
b1111 "
0!
$end
#3000
0#
#5000
b10 &
b10 -
b10 $
b10 +
b10 .
b100100 '
b100100 /
1)
b101 %
b101 *
b101 ,
1!
#10000
0!
#15000
b1 &
b1 -
b1 $
b1 +
b1 .
b1001111 '
b1001111 /
0)
b1 %
b1 *
b1 ,
1!
#20000
0!
#25000
b10 &
b10 -
b10 $
b10 +
b10 .
b100100 '
b100100 /
1)
b101 %
b101 *
b101 ,
1!
#30000
0!
#35000
b1 &
b1 -
b1 $
b1 +
b1 .
b1001111 '
b1001111 /
0)
b1 %
b1 *
b1 ,
1!
#40000
0!
#45000
b10 &
b10 -
b10 $
b10 +
b10 .
b100100 '
b100100 /
1)
b101 %
b101 *
b101 ,
1!
#50000
0!
#55000
b1 &
b1 -
b1 $
b1 +
b1 .
b1001111 '
b1001111 /
0)
b1 %
b1 *
b1 ,
1!
#60000
0!
#65000
b10 &
b10 -
b10 $
b10 +
b10 .
b100100 '
b100100 /
1)
b101 %
b101 *
b101 ,
1!
#70000
0!
#75000
b1 &
b1 -
b1 $
b1 +
b1 .
b1001111 '
b1001111 /
0)
b1 %
b1 *
b1 ,
1!
