src/BCDtoSSeg.v
module BCDtoSSeg (
    input [3:0] BCD, 
    input [3:0] c,
    output reg [0:6] SSeg, 
    output [3:0] an
  );
  
  assign an = c;

  always @ ( * ) begin
    case (BCD)
      4'b0000: SSeg = 7'b0000001; // "0"  
  	  4'b0001: SSeg = 7'b1001111; // "1" 
  	  4'b0010: SSeg = 7'b0010010; // "2" 
  	  4'b0011: SSeg = 7'b0000110; // "3" 
  	  4'b0100: SSeg = 7'b1001100; // "4" 
  	  4'b0101: SSeg = 7'b0100100; // "5" 
  	  4'b0110: SSeg = 7'b0100000; // "6" 
  	  4'b0111: SSeg = 7'b0001111; // "7" 
  	  4'b1000: SSeg = 7'b0000000; // "8"  
  	  4'b1001: SSeg = 7'b0000100; // "9"
      4'b1100: SSeg = 7'b1111110; // menos
      4'ha: SSeg = 7'b0001000;  
      4'hb: SSeg = 7'b1100000;
      4'hc: SSeg = 7'b0110001;
      4'hd: SSeg = 7'b1000010;
      4'he: SSeg = 7'b0110000;
      4'hf: SSeg = 7'b0111000;
       default: SSeg = 7'b0000000;
    endcase
  end

endmodule

src/CF_Div.v
module CF_Div(

    input clk,
    output reg fdiv
);

// 8000000 para quartus aprox, en testbench toca poner como 10

reg [$clog2(200000):0] counter;

    initial begin
        fdiv = 1'b0;
		  counter = 'b0;
    end

always@(posedge clk) begin
    if (counter == 200000) begin
        counter <= 0;
        fdiv <= ~fdiv;
    end else begin
        counter <= counter +1;
    end
end


endmodule

src/BCD.v
module BCD (
    input [4:0] inp,  
    input clk2,
    input rst,
    input Sel,
    output reg [3:0] bcd,
    output reg [3:0] c
  );

  //reg  algo = 0; esto se cambia por el rst
  reg [1:0]algo;
    
  initial begin
		algo = 2'b00;
		c = 'b0;
  end
  

  always@(posedge clk2) begin
      case(algo)
        0:begin
          bcd<=inp%10;
          algo <= 1;
			 c <= 4'b1110;
          end
        1:begin
          bcd<=(inp-inp%10)/10;
          if (Sel ==1 && inp[4]==0) begin
            algo <= 2'b10;
          end else begin
            algo <= 0;
          end
			 c <= 4'b1101;
          end
        2: begin
          bcd <= 4'b1100;
          algo <= 0;
          c <= 4'b1011;
        end
      endcase
  end
endmodule

src/top.v
//`include "src/BCD.v"
//`include "src/CF_Div.v"
//`include "src/BCDtoSSeg.v"

module top (
    input [4:0] inp,  
    input clk,
    input rst,
    input Sel,
    output [0:6] SSeg, 
    output [3:0] an

);
    wire [3:0]bcdsseg;
    wire [3:0]c;
    wire fdividier;

    BCD BCD(
    .bcd(bcdsseg),
    .inp(inp),
    .rst(rst),
    .c(c),
    .Sel(Sel),
    .clk2(fdivider)
    );

    CF_Div fdiv(
    .clk(clk),
    .fdiv(fdivider)
    );

    BCDtoSSeg BCDtoSSeg(
    .SSeg(SSeg),
    .c(c),
    .BCD(bcdsseg),
    .an(an)
    );

endmodule

src/sum1b_estruc.v
module sum1b_estruc (
    input A, 
    input B, 
    input Ci,
    output Cout,
    output S
  );

  //Enfoque estructrural - nivel gates.
  
    wire a_ab;
    wire x_ab;
    wire cout_t;
  
    and(a_ab,A,B); //assing a_ab = A&B - x
    xor(S,x_ab,Ci);
    xor(x_ab,A,B);
    and(cout_t,x_ab,Ci);
    or (Cout,cout_t,a_ab);
  
  endmodule

src/sum4b_estruc.v
//`include "src/sum1b_estruc.v"

module sum4b_estruc(

    input [3:0] A,
    input [3:0] B,
    input Ci, 
    output Cout,
    output [3:0] S

    );

    wire c0; wire c1; wire c2;

    sum1b_estruc S0 (.A(A[0]),
                     .B(B[0]),
                     .Ci(Ci),
                     .Cout(c0),
                     .S(S[0]));

    sum1b_estruc S1 (.A(A[1]),
                     .B(B[1]),
                     .Ci(c0),
                     .Cout(c1),
                     .S(S[1]));
    
    sum1b_estruc S2 (.A(A[2]),
                     .B(B[2]),
                     .Ci(c1),
                     .Cout(c2),
                     .S(S[2]));
    
    sum1b_estruc S3 (.A(A[3]),
                     .B(B[3]),
                     .Ci(c2),
                     .Cout(Cout),
                     .S(S[3]));
endmodule

src/sum_res_4b.v
`include "src/sum4b_estruc.v"

module sum_res_4b(

    input [3:0] A,
    input [3:0] B,
    input Sel, 
    output Cout,
    output [3:0] S

    );

    wire [3:0] B_c;
    assign B_c = B^{4{Sel}};
    wire c0, c1, c2;

    sum4b_estruc UUT (
        .A(A)
        .B(B_c)
        .Ci(Sel)
        .S(S),
        .Cout(Cout)
    );

endmodule

src/top_sum_res.v


module top_sum_res(
    input [3:0] A,
    input [3:0] B,
    input Sel,
    input clk,
    input rst,
    output [0:6] SSeg,
    output [3:0] an
    );

    wire Cout;
    wire [3:0] S;
    wire [4:0] inp_top;

    assign inp_top = {Cout, S};

    sum_res_4b sr (
        .A(A),
        .B(B),
        .Sel(Sel),
        .Cout(Cout),
        .S(S)
    );

    top u_top (
        .inp(inp_top),
        .clk(clk),
        .rst(rst),
        .Sel(Sel),
        .SSeg(SSeg),
        .an(an)
    );

endmodule

src/top_sum_res_tb.v
`timescale 1ns/1ps
`include "src/top_sum_res.v"
`include "src/sum_res_4b.v"
`include "src/top.v"
`include "src/BCD.v"
`include "src/CF_Div.v"
`include "src/BCDtoSSeg.v"
`include "src/sum4b_estruc.v"
`include "src/sum1b_estruc.v"

module top_sum_res_tb();
    reg [3:0] A;
    reg [3:0] B;
    reg Sel;
    reg clk;
    reg rst;
    
    wire [0:6] SSeg;
    wire [3:0] an;

    top_sum_res TSR (
        .A(A),
        .B(B),
        .Sel(Sel),
        .clk(clk),
        .rst(rst),
        .SSeg(SSeg),
        .an(an)
    );

    always begin
        clk = ~clk;
        #5;
    end

    initial begin

        A = 0;
        B = 0;
        Sel = 0;
        clk = 0;
        rst = 1;
        #100;

        rst = 0;

        A = 4'd2;
        B = 4'd3;
        Sel = 1;
        #500;

    end

    initial begin
        $dumpfile("top_sum_res_tb.vcd");
        $dumpvars(0, top_sum_res_tb);
        #10000 $finish;
    end

endmodule

build/top_sum_res_tb.vcd
$date
	Thu Jul  3 12:18:34 2025
$end
$version
	Icarus Verilog
$end
$timescale
	1ps
$end
$scope module top_sum_res_tb $end
$var wire 4 ! an [3:0] $end
$var wire 7 " SSeg [0:6] $end
$var reg 4 # A [3:0] $end
$var reg 4 $ B [3:0] $end
$var reg 1 % Sel $end
$var reg 1 & clk $end
$var reg 1 ' rst $end
$scope module TSR $end
$var wire 4 ( A [3:0] $end
$var wire 4 ) B [3:0] $end
$var wire 1 % Sel $end
$var wire 1 & clk $end
$var wire 1 ' rst $end
$var wire 5 * inp_top [4:0] $end
$var wire 4 + an [3:0] $end
$var wire 7 , SSeg [0:6] $end
$var wire 4 - S [3:0] $end
$var wire 1 . Cout $end
$scope module sr $end
$var wire 4 / A [3:0] $end
$var wire 4 0 B [3:0] $end
$var wire 4 1 B_c [3:0] $end
$var wire 1 % Sel $end
$var wire 4 2 S [3:0] $end
$var wire 1 . Cout $end
$scope module UUT $end
$var wire 4 3 A [3:0] $end
$var wire 4 4 B [3:0] $end
$var wire 1 % Ci $end
$var wire 1 5 c2 $end
$var wire 1 6 c1 $end
$var wire 1 7 c0 $end
$var wire 4 8 S [3:0] $end
$var wire 1 . Cout $end
$scope module S0 $end
$var wire 1 9 A $end
$var wire 1 : B $end
$var wire 1 % Ci $end
$var wire 1 7 Cout $end
$var wire 1 ; S $end
$var wire 1 < a_ab $end
$var wire 1 = cout_t $end
$var wire 1 > x_ab $end
$upscope $end
$scope module S1 $end
$var wire 1 ? A $end
$var wire 1 @ B $end
$var wire 1 7 Ci $end
$var wire 1 6 Cout $end
$var wire 1 A S $end
$var wire 1 B a_ab $end
$var wire 1 C cout_t $end
$var wire 1 D x_ab $end
$upscope $end
$scope module S2 $end
$var wire 1 E A $end
$var wire 1 F B $end
$var wire 1 6 Ci $end
$var wire 1 5 Cout $end
$var wire 1 G S $end
$var wire 1 H a_ab $end
$var wire 1 I cout_t $end
$var wire 1 J x_ab $end
$upscope $end
$scope module S3 $end
$var wire 1 K A $end
$var wire 1 L B $end
$var wire 1 5 Ci $end
$var wire 1 . Cout $end
$var wire 1 M S $end
$var wire 1 N a_ab $end
$var wire 1 O cout_t $end
$var wire 1 P x_ab $end
$upscope $end
$upscope $end
$upscope $end
$scope module u_top $end
$var wire 1 % Sel $end
$var wire 1 & clk $end
$var wire 5 Q inp [4:0] $end
$var wire 1 ' rst $end
$var wire 1 R fdivider $end
$var wire 4 S c [3:0] $end
$var wire 4 T bcdsseg [3:0] $end
$var wire 4 U an [3:0] $end
$var wire 7 V SSeg [0:6] $end
$scope module BCD $end
$var wire 1 % Sel $end
$var wire 5 W inp [4:0] $end
$var wire 1 ' rst $end
$var wire 1 R clk2 $end
$var reg 2 X algo [1:0] $end
$var reg 4 Y bcd [3:0] $end
$var reg 4 Z c [3:0] $end
$upscope $end
$scope module BCDtoSSeg $end
$var wire 4 [ BCD [3:0] $end
$var wire 4 \ an [3:0] $end
$var wire 4 ] c [3:0] $end
$var reg 7 ^ SSeg [0:6] $end
$upscope $end
$scope module fdiv $end
$var wire 1 & clk $end
$var reg 5 _ counter [4:0] $end
$var reg 1 R fdiv $end
$upscope $end
$upscope $end
$upscope $end
$upscope $end
$enddefinitions $end
$comment Show the parameter values. $end
$dumpall
$end
#0
$dumpvars
b0 _
bx ^
b0 ]
b0 \
bx [
b0 Z
bx Y
b0 X
b0 W
bx V
b0 U
bx T
b0 S
0R
b0 Q
0P
0O
0N
0M
0L
0K
0J
0I
0H
0G
0F
0E
0D
0C
0B
0A
0@
0?
0>
0=
0<
0;
0:
09
b0 8
07
06
05
b0 4
b0 3
b0 2
b0 1
b0 0
b0 /
0.
b0 -
bx ,
b0 +
b0 *
b0 )
b0 (
1'
0&
0%
b0 $
b0 #
bx "
b0 !
$end
#5000
b1 _
1&
#10000
0&
#15000
b10 _
1&
#20000
0&
#25000
b11 _
1&
#30000
0&
#35000
b100 _
1&
#40000
0&
#45000
b101 _
1&
#50000
0&
#55000
b110 _
1&
#60000
0&
#65000
b111 _
1&
#70000
0&
#75000
b1000 _
1&
#80000
0&
#85000
b1001 _
1&
#90000
0&
#95000
b1010 _
1&
#100000
1G
1M
1J
1P
1A
1F
1L
1D
b1111 *
b1111 Q
b1111 W
b1111 -
b1111 2
b1111 8
1;
b1100 1
b1100 4
1?
0&
1%
b11 $
b11 )
b11 0
b10 #
b10 (
b10 /
b10 3
0'
#105000
b100100 "
b100100 ,
b100100 V
b100100 ^
b1110 !
b1110 +
b1110 U
b1110 \
b1110 S
b1110 Z
b1110 ]
b1 X
b101 T
b101 Y
b101 [
1R
b0 _
1&
#110000
0&
#115000
b1 _
1&
#120000
0&
#125000
b10 _
1&
#130000
0&
#135000
b11 _
1&
#140000
0&
#145000
b100 _
1&
#150000
0&
#155000
b101 _
1&
#160000
0&
#165000
b110 _
1&
#170000
0&
#175000
b111 _
1&
#180000
0&
#185000
b1000 _
1&
#190000
0&
#195000
b1001 _
1&
#200000
0&
#205000
b1010 _
1&
#210000
0&
#215000
0R
b0 _
1&
#220000
0&
#225000
b1 _
1&
#230000
0&
#235000
b10 _
1&
#240000
0&
#245000
b11 _
1&
#250000
0&
#255000
b100 _
1&
#260000
0&
#265000
b101 _
1&
#270000
0&
#275000
b110 _
1&
#280000
0&
#285000
b111 _
1&
#290000
0&
#295000
b1000 _
1&
#300000
0&
#305000
b1001 _
1&
#310000
0&
#315000
b1010 _
1&
#320000
0&
#325000
b1001111 "
b1001111 ,
b1001111 V
b1001111 ^
b1101 !
b1101 +
b1101 U
b1101 \
b1101 S
b1101 Z
b1101 ]
b10 X
b1 T
b1 Y
b1 [
1R
b0 _
1&
#330000
0&
#335000
b1 _
1&
#340000
0&
#345000
b10 _
1&
#350000
0&
#355000
b11 _
1&
#360000
0&
#365000
b100 _
1&
#370000
0&
#375000
b101 _
1&
#380000
0&
#385000
b110 _
1&
#390000
0&
#395000
b111 _
1&
#400000
0&
#405000
b1000 _
1&
#410000
0&
#415000
b1001 _
1&
#420000
0&
#425000
b1010 _
1&
#430000
0&
#435000
0R
b0 _
1&
#440000
0&
#445000
b1 _
1&
#450000
0&
#455000
b10 _
1&
#460000
0&
#465000
b11 _
1&
#470000
0&
#475000
b100 _
1&
#480000
0&
#485000
b101 _
1&
#490000
0&
#495000
b110 _
1&
#500000
0&
#505000
b111 _
1&
#510000
0&
#515000
b1000 _
1&
#520000
0&
#525000
b1001 _
1&
#530000
0&
#535000
b1010 _
1&
#540000
0&
#545000
b10 "
b10 ,
b10 V
b10 ^
b1011 !
b1011 +
b1011 U
b1011 \
b1011 S
b1011 Z
b1011 ]
b0 X
b1100 T
b1100 Y
b1100 [
1R
b0 _
1&
#550000
0&
#555000
b1 _
1&
#560000
0&
#565000
b10 _
1&
#570000
0&
#575000
b11 _
1&
#580000
0&
#585000
b100 _
1&
#590000
0&
#595000
b101 _
1&
#600000
0&
#605000
b110 _
1&
#610000
0&
#615000
b111 _
1&
#620000
0&
#625000
b1000 _
1&
#630000
0&
#635000
b1001 _
1&
#640000
0&
#645000
b1010 _
1&
#650000
0&
#655000
0R
b0 _
1&
#660000
0&
#665000
b1 _
1&
#670000
0&
#675000
b10 _
1&
#680000
0&
#685000
b11 _
1&
#690000
0&
#695000
b100 _
1&
#700000
0&
#705000
b101 _
1&
#710000
0&
#715000
b110 _
1&
#720000
0&
#725000
b111 _
1&
#730000
0&
#735000
b1000 _
1&
#740000
0&
#745000
b1001 _
1&
#750000
0&
#755000
b1010 _
1&
#760000
0&
#765000
b100100 "
b100100 ,
b100100 V
b100100 ^
b1110 !
b1110 +
b1110 U
b1110 \
b1110 S
b1110 Z
b1110 ]
b1 X
b101 T
b101 Y
b101 [
1R
b0 _
1&
#770000
0&
#775000
b1 _
1&
#780000
0&
#785000
b10 _
1&
#790000
0&
#795000
b11 _
1&
#800000
0&
#805000
b100 _
1&
#810000
0&
#815000
b101 _
1&
#820000
0&
#825000
b110 _
1&
#830000
0&
#835000
b111 _
1&
#840000
0&
#845000
b1000 _
1&
#850000
0&
#855000
b1001 _
1&
#860000
0&
#865000
b1010 _
1&
#870000
0&
#875000
0R
b0 _
1&
#880000
0&
#885000
b1 _
1&
#890000
0&
#895000
b10 _
1&
#900000
0&
#905000
b11 _
1&
#910000
0&
#915000
b100 _
1&
#920000
0&
#925000
b101 _
1&
#930000
0&
#935000
b110 _
1&
#940000
0&
#945000
b111 _
1&
#950000
0&
#955000
b1000 _
1&
#960000
0&
#965000
b1001 _
1&
#970000
0&
#975000
b1010 _
1&
#980000
0&
#985000
b1001111 "
b1001111 ,
b1001111 V
b1001111 ^
b1101 !
b1101 +
b1101 U
b1101 \
b1101 S
b1101 Z
b1101 ]
b10 X
b1 T
b1 Y
b1 [
1R
b0 _
1&
#990000
0&
#995000
b1 _
1&
#1000000
0&
#1005000
b10 _
1&
#1010000
0&
#1015000
b11 _
1&
#1020000
0&
#1025000
b100 _
1&
#1030000
0&
#1035000
b101 _
1&
#1040000
0&
#1045000
b110 _
1&
#1050000
0&
#1055000
b111 _
1&
#1060000
0&
#1065000
b1000 _
1&
#1070000
0&
#1075000
b1001 _
1&
#1080000
0&
#1085000
b1010 _
1&
#1090000
0&
#1095000
0R
b0 _
1&
#1100000
0&
#1105000
b1 _
1&
#1110000
0&
#1115000
b10 _
1&
#1120000
0&
#1125000
b11 _
1&
#1130000
0&
#1135000
b100 _
1&
#1140000
0&
#1145000
b101 _
1&
#1150000
0&
#1155000
b110 _
1&
#1160000
0&
#1165000
b111 _
1&
#1170000
0&
#1175000
b1000 _
1&
#1180000
0&
#1185000
b1001 _
1&
#1190000
0&
#1195000
b1010 _
1&
#1200000
0&
#1205000
b10 "
b10 ,
b10 V
b10 ^
b1011 !
b1011 +
b1011 U
b1011 \
b1011 S
b1011 Z
b1011 ]
b0 X
b1100 T
b1100 Y
b1100 [
1R
b0 _
1&
#1210000
0&
#1215000
b1 _
1&
#1220000
0&
#1225000
b10 _
1&
#1230000
0&
#1235000
b11 _
1&
#1240000
0&
#1245000
b100 _
1&
#1250000
0&
#1255000
b101 _
1&
#1260000
0&
#1265000
b110 _
1&
#1270000
0&
#1275000
b111 _
1&
#1280000
0&
#1285000
b1000 _
1&
#1290000
0&
#1295000
b1001 _
1&
#1300000
0&
#1305000
b1010 _
1&
#1310000
0&
#1315000
0R
b0 _
1&
#1320000
0&
#1325000
b1 _
1&
#1330000
0&
#1335000
b10 _
1&
#1340000
0&
#1345000
b11 _
1&
#1350000
0&
#1355000
b100 _
1&
#1360000
0&
#1365000
b101 _
1&
#1370000
0&
#1375000
b110 _
1&
#1380000
0&
#1385000
b111 _
1&
#1390000
0&
#1395000
b1000 _
1&
#1400000
0&
#1405000
b1001 _
1&
#1410000
0&
#1415000
b1010 _
1&
#1420000
0&
#1425000
b100100 "
b100100 ,
b100100 V
b100100 ^
b1110 !
b1110 +
b1110 U
b1110 \
b1110 S
b1110 Z
b1110 ]
b1 X
b101 T
b101 Y
b101 [
1R
b0 _
1&
#1430000
0&
#1435000
b1 _
1&
#1440000
0&
#1445000
b10 _
1&
#1450000
0&
#1455000
b11 _
1&
#1460000
0&
#1465000
b100 _
1&
#1470000
0&
#1475000
b101 _
1&
#1480000
0&
#1485000
b110 _
1&
#1490000
0&
#1495000
b111 _
1&
#1500000
0&
#1505000
b1000 _
1&
#1510000
0&
#1515000
b1001 _
1&
#1520000
0&
#1525000
b1010 _
1&
#1530000
0&
#1535000
0R
b0 _
1&
#1540000
0&
#1545000
b1 _
1&
#1550000
0&
#1555000
b10 _
1&
#1560000
0&
#1565000
b11 _
1&
#1570000
0&
#1575000
b100 _
1&
#1580000
0&
#1585000
b101 _
1&
#1590000
0&
#1595000
b110 _
1&
#1600000
0&
#1605000
b111 _
1&
#1610000
0&
#1615000
b1000 _
1&
#1620000
0&
#1625000
b1001 _
1&
#1630000
0&
#1635000
b1010 _
1&
#1640000
0&
#1645000
b1001111 "
b1001111 ,
b1001111 V
b1001111 ^
b1101 !
b1101 +
b1101 U
b1101 \
b1101 S
b1101 Z
b1101 ]
b10 X
b1 T
b1 Y
b1 [
1R
b0 _
1&
#1650000
0&
#1655000
b1 _
1&
#1660000
0&
#1665000
b10 _
1&
#1670000
0&
#1675000
b11 _
1&
#1680000
0&
#1685000
b100 _
1&
#1690000
0&
#1695000
b101 _
1&
#1700000
0&
#1705000
b110 _
1&
#1710000
0&
#1715000
b111 _
1&
#1720000
0&
#1725000
b1000 _
1&
#1730000
0&
#1735000
b1001 _
1&
#1740000
0&
#1745000
b1010 _
1&
#1750000
0&
#1755000
0R
b0 _
1&
#1760000
0&
#1765000
b1 _
1&
#1770000
0&
#1775000
b10 _
1&
#1780000
0&
#1785000
b11 _
1&
#1790000
0&
#1795000
b100 _
1&
#1800000
0&
#1805000
b101 _
1&
#1810000
0&
#1815000
b110 _
1&
#1820000
0&
#1825000
b111 _
1&
#1830000
0&
#1835000
b1000 _
1&
#1840000
0&
#1845000
b1001 _
1&
#1850000
0&
#1855000
b1010 _
1&
#1860000
0&
#1865000
b10 "
b10 ,
b10 V
b10 ^
b1011 !
b1011 +
b1011 U
b1011 \
b1011 S
b1011 Z
b1011 ]
b0 X
b1100 T
b1100 Y
b1100 [
1R
b0 _
1&
#1870000
0&
#1875000
b1 _
1&
#1880000
0&
#1885000
b10 _
1&
#1890000
0&
#1895000
b11 _
1&
#1900000
0&
#1905000
b100 _
1&
#1910000
0&
#1915000
b101 _
1&
#1920000
0&
#1925000
b110 _
1&
#1930000
0&
#1935000
b111 _
1&
#1940000
0&
#1945000
b1000 _
1&
#1950000
0&
#1955000
b1001 _
1&
#1960000
0&
#1965000
b1010 _
1&
#1970000
0&
#1975000
0R
b0 _
1&
#1980000
0&
#1985000
b1 _
1&
#1990000
0&
#1995000
b10 _
1&
#2000000
0&
#2005000
b11 _
1&
#2010000
0&
#2015000
b100 _
1&
#2020000
0&
#2025000
b101 _
1&
#2030000
0&
#2035000
b110 _
1&
#2040000
0&
#2045000
b111 _
1&
#2050000
0&
#2055000
b1000 _
1&
#2060000
0&
#2065000
b1001 _
1&
#2070000
0&
#2075000
b1010 _
1&
#2080000
0&
#2085000
b100100 "
b100100 ,
b100100 V
b100100 ^
b1110 !
b1110 +
b1110 U
b1110 \
b1110 S
b1110 Z
b1110 ]
b1 X
b101 T
b101 Y
b101 [
1R
b0 _
1&
#2090000
0&
#2095000
b1 _
1&
#2100000
0&
#2105000
b10 _
1&
#2110000
0&
#2115000
b11 _
1&
#2120000
0&
#2125000
b100 _
1&
#2130000
0&
#2135000
b101 _
1&
#2140000
0&
#2145000
b110 _
1&
#2150000
0&
#2155000
b111 _
1&
#2160000
0&
#2165000
b1000 _
1&
#2170000
0&
#2175000
b1001 _
1&
#2180000
0&
#2185000
b1010 _
1&
#2190000
0&
#2195000
0R
b0 _
1&
#2200000
0&
#2205000
b1 _
1&
#2210000
0&
#2215000
b10 _
1&
#2220000
0&
#2225000
b11 _
1&
#2230000
0&
#2235000
b100 _
1&
#2240000
0&
#2245000
b101 _
1&
#2250000
0&
#2255000
b110 _
1&
#2260000
0&
#2265000
b111 _
1&
#2270000
0&
#2275000
b1000 _
1&
#2280000
0&
#2285000
b1001 _
1&
#2290000
0&
#2295000
b1010 _
1&
#2300000
0&
#2305000
b1001111 "
b1001111 ,
b1001111 V
b1001111 ^
b1101 !
b1101 +
b1101 U
b1101 \
b1101 S
b1101 Z
b1101 ]
b10 X
b1 T
b1 Y
b1 [
1R
b0 _
1&
#2310000
0&
#2315000
b1 _
1&
#2320000
0&
#2325000
b10 _
1&
#2330000
0&
#2335000
b11 _
1&
#2340000
0&
#2345000
b100 _
1&
#2350000
0&
#2355000
b101 _
1&
#2360000
0&
#2365000
b110 _
1&
#2370000
0&
#2375000
b111 _
1&
#2380000
0&
#2385000
b1000 _
1&
#2390000
0&
#2395000
b1001 _
1&
#2400000
0&
#2405000
b1010 _
1&
#2410000
0&
#2415000
0R
b0 _
1&
#2420000
0&
#2425000
b1 _
1&
#2430000
0&
#2435000
b10 _
1&
#2440000
0&
#2445000
b11 _
1&
#2450000
0&
#2455000
b100 _
1&
#2460000
0&
#2465000
b101 _
1&
#2470000
0&
#2475000
b110 _
1&
#2480000
0&
#2485000
b111 _
1&
#2490000
0&
#2495000
b1000 _
1&
#2500000
0&
#2505000
b1001 _
1&
#2510000
0&
#2515000
b1010 _
1&
#2520000
0&
#2525000
b10 "
b10 ,
b10 V
b10 ^
b1011 !
b1011 +
b1011 U
b1011 \
b1011 S
b1011 Z
b1011 ]
b0 X
b1100 T
b1100 Y
b1100 [
1R
b0 _
1&
#2530000
0&
#2535000
b1 _
1&
#2540000
0&
#2545000
b10 _
1&
#2550000
0&
#2555000
b11 _
1&
#2560000
0&
#2565000
b100 _
1&
#2570000
0&
#2575000
b101 _
1&
#2580000
0&
#2585000
b110 _
1&
#2590000
0&
#2595000
b111 _
1&
#2600000
0&
#2605000
b1000 _
1&
#2610000
0&
#2615000
b1001 _
1&
#2620000
0&
#2625000
b1010 _
1&
#2630000
0&
#2635000
0R
b0 _
1&
#2640000
0&
#2645000
b1 _
1&
#2650000
0&
#2655000
b10 _
1&
#2660000
0&
#2665000
b11 _
1&
#2670000
0&
#2675000
b100 _
1&
#2680000
0&
#2685000
b101 _
1&
#2690000
0&
#2695000
b110 _
1&
#2700000
0&
#2705000
b111 _
1&
#2710000
0&
#2715000
b1000 _
1&
#2720000
0&
#2725000
b1001 _
1&
#2730000
0&
#2735000
b1010 _
1&
#2740000
0&
#2745000
b100100 "
b100100 ,
b100100 V
b100100 ^
b1110 !
b1110 +
b1110 U
b1110 \
b1110 S
b1110 Z
b1110 ]
b1 X
b101 T
b101 Y
b101 [
1R
b0 _
1&
#2750000
0&
#2755000
b1 _
1&
#2760000
0&
#2765000
b10 _
1&
#2770000
0&
#2775000
b11 _
1&
#2780000
0&
#2785000
b100 _
1&
#2790000
0&
#2795000
b101 _
1&
#2800000
0&
#2805000
b110 _
1&
#2810000
0&
#2815000
b111 _
1&
#2820000
0&
#2825000
b1000 _
1&
#2830000
0&
#2835000
b1001 _
1&
#2840000
0&
#2845000
b1010 _
1&
#2850000
0&
#2855000
0R
b0 _
1&
#2860000
0&
#2865000
b1 _
1&
#2870000
0&
#2875000
b10 _
1&
#2880000
0&
#2885000
b11 _
1&
#2890000
0&
#2895000
b100 _
1&
#2900000
0&
#2905000
b101 _
1&
#2910000
0&
#2915000
b110 _
1&
#2920000
0&
#2925000
b111 _
1&
#2930000
0&
#2935000
b1000 _
1&
#2940000
0&
#2945000
b1001 _
1&
#2950000
0&
#2955000
b1010 _
1&
#2960000
0&
#2965000
b1001111 "
b1001111 ,
b1001111 V
b1001111 ^
b1101 !
b1101 +
b1101 U
b1101 \
b1101 S
b1101 Z
b1101 ]
b10 X
b1 T
b1 Y
b1 [
1R
b0 _
1&
#2970000
0&
#2975000
b1 _
1&
#2980000
0&
#2985000
b10 _
1&
#2990000
0&
#2995000
b11 _
1&
#3000000
0&
#3005000
b100 _
1&
#3010000
0&
#3015000
b101 _
1&
#3020000
0&
#3025000
b110 _
1&
#3030000
0&
#3035000
b111 _
1&
#3040000
0&
#3045000
b1000 _
1&
#3050000
0&
#3055000
b1001 _
1&
#3060000
0&
#3065000
b1010 _
1&
#3070000
0&
#3075000
0R
b0 _
1&
#3080000
0&
#3085000
b1 _
1&
#3090000
0&
#3095000
b10 _
1&
#3100000
0&
#3105000
b11 _
1&
#3110000
0&
#3115000
b100 _
1&
#3120000
0&
#3125000
b101 _
1&
#3130000
0&
#3135000
b110 _
1&
#3140000
0&
#3145000
b111 _
1&
#3150000
0&
#3155000
b1000 _
1&
#3160000
0&
#3165000
b1001 _
1&
#3170000
0&
#3175000
b1010 _
1&
#3180000
0&
#3185000
b10 "
b10 ,
b10 V
b10 ^
b1011 !
b1011 +
b1011 U
b1011 \
b1011 S
b1011 Z
b1011 ]
b0 X
b1100 T
b1100 Y
b1100 [
1R
b0 _
1&
#3190000
0&
#3195000
b1 _
1&
#3200000
0&
#3205000
b10 _
1&
#3210000
0&
#3215000
b11 _
1&
#3220000
0&
#3225000
b100 _
1&
#3230000
0&
#3235000
b101 _
1&
#3240000
0&
#3245000
b110 _
1&
#3250000
0&
#3255000
b111 _
1&
#3260000
0&
#3265000
b1000 _
1&
#3270000
0&
#3275000
b1001 _
1&
#3280000
0&
#3285000
b1010 _
1&
#3290000
0&
#3295000
0R
b0 _
1&
#3300000
0&
#3305000
b1 _
1&
#3310000
0&
#3315000
b10 _
1&
#3320000
0&
#3325000
b11 _
1&
#3330000
0&
#3335000
b100 _
1&
#3340000
0&
#3345000
b101 _
1&
#3350000
0&
#3355000
b110 _
1&
#3360000
0&
#3365000
b111 _
1&
#3370000
0&
#3375000
b1000 _
1&
#3380000
0&
#3385000
b1001 _
1&
#3390000
0&
#3395000
b1010 _
1&
#3400000
0&
#3405000
b100100 "
b100100 ,
b100100 V
b100100 ^
b1110 !
b1110 +
b1110 U
b1110 \
b1110 S
b1110 Z
b1110 ]
b1 X
b101 T
b101 Y
b101 [
1R
b0 _
1&
#3410000
0&
#3415000
b1 _
1&
#3420000
0&
#3425000
b10 _
1&
#3430000
0&
#3435000
b11 _
1&
#3440000
0&
#3445000
b100 _
1&
#3450000
0&
#3455000
b101 _
1&
#3460000
0&
#3465000
b110 _
1&
#3470000
0&
#3475000
b111 _
1&
#3480000
0&
#3485000
b1000 _
1&
#3490000
0&
#3495000
b1001 _
1&
#3500000
0&
#3505000
b1010 _
1&
#3510000
0&
#3515000
0R
b0 _
1&
#3520000
0&
#3525000
b1 _
1&
#3530000
0&
#3535000
b10 _
1&
#3540000
0&
#3545000
b11 _
1&
#3550000
0&
#3555000
b100 _
1&
#3560000
0&
#3565000
b101 _
1&
#3570000
0&
#3575000
b110 _
1&
#3580000
0&
#3585000
b111 _
1&
#3590000
0&
#3595000
b1000 _
1&
#3600000
0&
#3605000
b1001 _
1&
#3610000
0&
#3615000
b1010 _
1&
#3620000
0&
#3625000
b1001111 "
b1001111 ,
b1001111 V
b1001111 ^
b1101 !
b1101 +
b1101 U
b1101 \
b1101 S
b1101 Z
b1101 ]
b10 X
b1 T
b1 Y
b1 [
1R
b0 _
1&
#3630000
0&
#3635000
b1 _
1&
#3640000
0&
#3645000
b10 _
1&
#3650000
0&
#3655000
b11 _
1&
#3660000
0&
#3665000
b100 _
1&
#3670000
0&
#3675000
b101 _
1&
#3680000
0&
#3685000
b110 _
1&
#3690000
0&
#3695000
b111 _
1&
#3700000
0&
#3705000
b1000 _
1&
#3710000
0&
#3715000
b1001 _
1&
#3720000
0&
#3725000
b1010 _
1&
#3730000
0&
#3735000
0R
b0 _
1&
#3740000
0&
#3745000
b1 _
1&
#3750000
0&
#3755000
b10 _
1&
#3760000
0&
#3765000
b11 _
1&
#3770000
0&
#3775000
b100 _
1&
#3780000
0&
#3785000
b101 _
1&
#3790000
0&
#3795000
b110 _
1&
#3800000
0&
#3805000
b111 _
1&
#3810000
0&
#3815000
b1000 _
1&
#3820000
0&
#3825000
b1001 _
1&
#3830000
0&
#3835000
b1010 _
1&
#3840000
0&
#3845000
b10 "
b10 ,
b10 V
b10 ^
b1011 !
b1011 +
b1011 U
b1011 \
b1011 S
b1011 Z
b1011 ]
b0 X
b1100 T
b1100 Y
b1100 [
1R
b0 _
1&
#3850000
0&
#3855000
b1 _
1&
#3860000
0&
#3865000
b10 _
1&
#3870000
0&
#3875000
b11 _
1&
#3880000
0&
#3885000
b100 _
1&
#3890000
0&
#3895000
b101 _
1&
#3900000
0&
#3905000
b110 _
1&
#3910000
0&
#3915000
b111 _
1&
#3920000
0&
#3925000
b1000 _
1&
#3930000
0&
#3935000
b1001 _
1&
#3940000
0&
#3945000
b1010 _
1&
#3950000
0&
#3955000
0R
b0 _
1&
